repoGist.py
repo_gist-0.1.1.dist-info/METADATA
repo_gist-0.1.1.dist-info/WHEEL
repo_gist-0.1.1.dist-info/entry_points.txt
repo_gist-0.1.1.dist-info/top_level.txt
repo_gist-0.1.1.dist-info/RECORD
