Metadata-Version: 2.1
Name: repo-gist
Version: 0.1.1
Summary: Create a gist from the contents of a repository, easy share with ChatGPT
Home-page: https://github.com/fire17/auto-repo-gist
Author: Tami
Author-email: fire17@gmail.com
Classifier: Programming Language :: Python :: 3
Classifier: License :: OSI Approved :: MIT License
Classifier: Operating System :: OS Independent
